FalconEDA/__init__.py
FalconEDA/app.py
FalconEDA/main.py
FalconEDA/make_pptx.py
FalconEDA/utils.py
FalconEDA-1.0.2.dist-info/LICENSE
FalconEDA-1.0.2.dist-info/METADATA
FalconEDA-1.0.2.dist-info/WHEEL
FalconEDA-1.0.2.dist-info/entry_points.txt
FalconEDA-1.0.2.dist-info/top_level.txt
FalconEDA-1.0.2.dist-info/RECORD
