Metadata-Version: 2.1
Name: FalconEDA
Version: 1.0.2
Summary: A Streamlit-based app for fast and interactive exploratory data analysis
Author: Riley Heiman
License: GNU General Public License v3.0 or later
Classifier: Programming Language :: Python :: 3
Classifier: License :: OSI Approved :: GNU General Public License v3 (GPLv3)
Classifier: Operating System :: OS Independent
Requires-Python: >=3.7
License-File: LICENSE
Requires-Dist: streamlit>=1.0
Requires-Dist: pandas>=1.3
Requires-Dist: numpy>=1.21
Requires-Dist: altair>=4.2
Requires-Dist: matplotlib
Requires-Dist: openpyxl
Requires-Dist: python-pptx
Requires-Dist: vl-convert-python
